{"category":{"name":"Enablers","normalized_name":"enablers","subcategories":[{"name":"Content Production","normalized_name":"content-production"}]},"foundation":"COMPOSABLE","items":[{"category":"Enablers","id":"enablers--content-production--creative-force","name":"Creative Force","logo":"logos/10002a0e3a9c52d533b6394ef198d4416e6bb4fdb1f4a111a64a5d2a3ee9091b.webp","subcategory":"Content Production","website":"https://creativeforce.io/","description":"Creative Force offers a content production platform that streamlines the workflow for creating digital assets."}]}